DESCRIPTION.rst
MANIFEST.in
setup.cfg
setup.py
daemon/systemd/marcodeployerd.service
daemon/systemd/marcoreceiverd.service
daemon/systemv/marcodeployerd
daemon/systemv/marcoreceiverd
etc/marcodeployer/deployer.cfg
etc/marcodeployer/secret
marcodeployer/__init__.py
marcodeployer/bufferprocessor.py
marcodeployer/conf.py
marcodeployer/create_home.py
marcodeployer/deployer.py
marcodeployer/receiver.py
marcodeployer/statusmonitor.py
marcodeployer/utils.py
marcopolo_deployer.egg-info/PKG-INFO
marcopolo_deployer.egg-info/SOURCES.txt
marcopolo_deployer.egg-info/dependency_links.txt
marcopolo_deployer.egg-info/entry_points.txt
marcopolo_deployer.egg-info/not-zip-safe
marcopolo_deployer.egg-info/requires.txt
marcopolo_deployer.egg-info/top_level.txt
usr/lib/marcodeployer/certs/app.crt
usr/lib/marcodeployer/certs/app.csr
usr/lib/marcodeployer/certs/app.key
usr/lib/marcodeployer/certs/receiver.crt
usr/lib/marcodeployer/certs/receiver.csr
usr/lib/marcodeployer/certs/receiver.key
usr/lib/marcodeployer/static/css/bootstrap.min.css
usr/lib/marcodeployer/static/css/style.css
usr/lib/marcodeployer/static/fonts/glyphicons-halflings-regular.eot
usr/lib/marcodeployer/static/fonts/glyphicons-halflings-regular.svg
usr/lib/marcodeployer/static/fonts/glyphicons-halflings-regular.ttf
usr/lib/marcodeployer/static/fonts/glyphicons-halflings-regular.woff
usr/lib/marcodeployer/static/img/wait.gif
usr/lib/marcodeployer/static/js/bootstrap.min.js
usr/lib/marcodeployer/static/js/d3.min.js
usr/lib/marcodeployer/static/js/gauge.js
usr/lib/marcodeployer/static/js/graphpolo.js
usr/lib/marcodeployer/static/js/jquery.cookie.js
usr/lib/marcodeployer/static/js/jquery.min.js
usr/lib/marcodeployer/static/js/jquery.min.map
usr/lib/marcodeployer/static/js/logger.js
usr/lib/marcodeployer/static/js/marco.js
usr/lib/marcodeployer/static/js/shell.js
usr/lib/marcodeployer/templates/403.jade
usr/lib/marcodeployer/templates/404.jade
usr/lib/marcodeployer/templates/500.jade
usr/lib/marcodeployer/templates/badpass.jade
usr/lib/marcodeployer/templates/base.jade
usr/lib/marcodeployer/templates/index.jade
usr/lib/marcodeployer/templates/login.jade