Metadata-Version: 1.1
Name: marcopolo-deployer
Version: 0.1.7
Summary: The deployer for the marcopolo environment
Home-page: marcopolo.martinarroyo.net/apps/marcodeployer
Author: Diego Martín
Author-email: martinarroyo@usal.es
License: MIT
Keywords: marcopolo deployer statusmonitor
Platform: UNKNOWN
Classifier: Development Status :: 3 - Alpha
Classifier: Intended Audience :: Developers
Classifier: Intended Audience :: System Administrators
Classifier: Topic :: Software Development
Classifier: Topic :: System :: Networking
Classifier: Topic :: System :: Monitoring
Classifier: License :: OSI Approved :: Mozilla Public License 2.0 (MPL 2.0)
Classifier: Programming Language :: Python :: 2.7
Classifier: Programming Language :: Python :: 3.4
Classifier: Natural Language :: English
Provides: marcodeployer
